{"learner":{"attributes":{},"feature_names":["Cow_ID","Day","Breed","Months after giving birth","Previous_Mastits_status","IUFL","EUFL","IUFR","EUFR","IURL","EURL","IURR","EURR","Temperature","Hardness","Pain","Milk_visibility"],"feature_types":["float","float","float","float","float","float","float","float","float","float","float","float","float","float","float","float","float"],"gradient_booster":{"model":{"gbtree_model_param":{"num_parallel_tree":"1","num_trees":"100"},"iteration_indptr":[0,1,2,3,4,5,6,7,8,9,10,11,12,13,14,15,16,17,18,19,20,21,22,23,24,25,26,27,28,29,30,31,32,33,34,35,36,37,38,39,40,41,42,43,44,45,46,47,48,49,50,51,52,53,54,55,56,57,58,59,60,61,62,63,64,65,66,67,68,69,70,71,72,73,74,75,76,77,78,79,80,81,82,83,84,85,86,87,88,89,90,91,92,93,94,95,96,97,98,99,100],"tree_info":[0,0,0,0,0,0,0,0,0,0,0,0,0,0,0,0,0,0,0,0,0,0,0,0,0,0,0,0,0,0,0,0,0,0,0,0,0,0,0,0,0,0,0,0,0,0,0,0,0,0,0,0,0,0,0,0,0,0,0,0,0,0,0,0,0,0,0,0,0,0,0,0,0,0,0,0,0,0,0,0,0,0,0,0,0,0,0,0,0,0,0,0,0,0,0,0,0,0,0,0],"trees":[{"base_weights":[-2.730955E-1,-1.2422695E0,4.68321E0,-1.2507595E-1,1.2443937E-1,1.1679264E-1,4.7089472E-1],"categories":[],"categories_nodes":[],"categories_segments":[],"categories_sizes":[],"default_left":[0,0,0,0,0,0,0],"id":0,"left_children":[1,3,5,-1,-1,-1,-1],"loss_changes":[3.367349E3,1.3930847E1,4.875E0,0E0,0E0,0E0,0E0],"parents":[2147483647,0,0,1,1,2,2],"right_children":[2,4,6,-1,-1,-1,-1],"split_conditions":[2.2385104E0,1.164739E0,4.7192056E-2,-1.2507595E-1,1.2443937E-1,1.1679264E-1,4.7089472E-1],"split_indices":[15,8,13,0,0,0,0],"split_type":[0,0,0,0,0,0,0],"sum_hessian":[6.988054E2,5.851353E2,1.13670135E2,5.8363965E2,1.4956597E0,1.1632909E0,1.1250684E2],"tree_param":{"num_deleted":"0","num_feature":"17","num_nodes":"7","size_leaf_vector":"1"}},{"base_weights":[-2.6005292E-1,-1.2128158E0,3.305694E0,-1.22003615E-1,1.2608922E-1,7.831178E-2,3.3189207E-1],"categories":[],"categories_nodes":[],"categories_segments":[],"categories_sizes":[],"default_left":[0,0,0,0,0,0,0],"id":1,"left_children":[1,3,5,-1,-1,-1,-1],"loss_changes":[2.333618E3,1.1216675E1,2.2340088E0,0E0,0E0,0E0,0E0],"parents":[2147483647,0,0,1,1,2,2],"right_children":[2,4,6,-1,-1,-1,-1],"split_conditions":[2.2385104E0,1.164739E0,4.7192056E-2,-1.22003615E-1,1.2608922E-1,7.831178E-2,3.3189207E-1],"split_indices":[15,8,13,0,0,0,0],"split_type":[0,0,0,0,0,0,0],"sum_hessian":[6.8472125E2,5.408632E2,1.4385806E2,5.3979443E2,1.0687821E0,1.064398E0,1.4279367E2],"tree_param":{"num_deleted":"0","num_feature":"17","num_nodes":"7","size_leaf_vector":"1"}},{"base_weights":[-2.4061537E-1,-1.2062079E-1,2.689402E-1],"categories":[],"categories_nodes":[],"categories_segments":[],"categories_sizes":[],"default_left":[0,0,0],"id":2,"left_children":[1,-1,-1],"loss_changes":[1.8944847E3,0E0,0E0],"parents":[2147483647,0,0],"right_children":[2,-1,-1],"split_conditions":[2.2239482E0,-1.2062079E-1,2.689402E-1],"split_indices":[16,0,0],"split_type":[0,0,0],"sum_hessian":[6.674712E2,5.0246976E2,1.6500146E2],"tree_param":{"num_deleted":"0","num_feature":"17","num_nodes":"3","size_leaf_vector":"1"}},{"base_weights":[-2.3142892E-1,-1.1572379E0,2.2656865E-1,-1.1631757E-1,6.192133E-2],"categories":[],"categories_nodes":[],"categories_segments":[],"categories_sizes":[],"default_left":[0,0,0,0,0],"id":3,"left_children":[1,3,-1,-1,-1],"loss_changes":[1.4861891E3,5.6654053E0,0E0,0E0,0E0],"parents":[2147483647,0,0,1,1],"right_children":[2,4,-1,-1,-1],"split_conditions":[2.2385104E0,1.5232676E0,2.2656865E-1,-1.1631757E-1,6.192133E-2],"split_indices":[15,7,0,0,0],"split_type":[0,0,0,0,0],"sum_hessian":[6.4072235E2,4.6781564E2,1.7290672E2,4.6660126E2,1.2143899E0],"tree_param":{"num_deleted":"0","num_feature":"17","num_nodes":"5","size_leaf_vector":"1"}},{"base_weights":[-2.1434255E-1,-1.1350741E0,1.9983469E-1,-1.1435806E-1,1.1972978E-1],"categories":[],"categories_nodes":[],"categories_segments":[],"categories_sizes":[],"default_left":[0,0,0,0,0],"id":4,"left_children":[1,3,-1,-1,-1],"loss_changes":[1.235205E3,9.860779E0,0E0,0E0,0E0],"parents":[2147483647,0,0,1,1],"right_children":[2,4,-1,-1,-1],"split_conditions":[4.7192056E-2,1.6076784E0,1.9983469E-1,-1.1435806E-1,1.1972978E-1],"split_indices":[13,7,0,0,0],"split_type":[0,0,0,0,0],"sum_hessian":[6.041838E2,4.2699295E2,1.7719083E2,4.2594916E2,1.0438098E0],"tree_param":{"num_deleted":"0","num_feature":"17","num_nodes":"5","size_leaf_vector":"1"}},{"base_weights":[-2.0794128E-1,-1.1171471E0,1.8041323E0,-1.12377085E-1,5.770124E-2,7.9322946E-1,1.8278357E-1,-7.51027E-2,1.5932448E-1],"categories":[],"categories_nodes":[],"categories_segments":[],"categories_sizes":[],"default_left":[0,0,0,0,0,0,0,0,0],"id":5,"left_children":[1,3,5,-1,-1,7,-1,-1,-1],"loss_changes":[1.0430708E3,5.0538025E0,2.8032227E0,0E0,0E0,8.403162E0,0E0,0E0,0E0],"parents":[2147483647,0,0,1,1,2,2,5,5],"right_children":[2,4,6,-1,-1,8,-1,-1,-1],"split_conditions":[4.7192056E-2,1.164739E0,2.2607768E0,-1.12377085E-1,5.770124E-2,-1.3777683E0,1.8278357E-1,-7.51027E-2,1.5932448E-1],"split_indices":[13,8,14,0,0,0,0,0,0],"split_type":[0,0,0,0,0,0,0,0,0],"sum_hessian":[5.6807263E2,3.9157465E2,1.7649802E2,3.90385E2,1.1896298E0,4.833271E0,1.7166475E2,1.6703179E0,3.1629531E0],"tree_param":{"num_deleted":"0","num_feature":"17","num_nodes":"9","size_leaf_vector":"1"}},{"base_weights":[-2.0992602E-1,-1.0966518E0,1.6825559E0,-1.10615805E-1,1.0520095E-1,7.580143E-1,1.6916315E-1,7.639367E-3,1.0059476E-1],"categories":[],"categories_nodes":[],"categories_segments":[],"categories_sizes":[],"default_left":[0,0,0,0,0,0,0,0,0],"id":6,"left_children":[1,3,5,-1,-1,7,-1,-1,-1],"loss_changes":[8.8983307E2,8.535919E0,1.3760376E-1,0E0,0E0,5.0736046E-1,0E0,0E0,0E0],"parents":[2147483647,0,0,1,1,2,2,5,5],"right_children":[2,4,6,-1,-1,8,-1,-1,-1],"split_conditions":[2.2385104E0,1.6076784E0,-1.1559621E0,-1.10615805E-1,1.0520095E-1,-1.25495E0,1.6916315E-1,7.639367E-3,1.0059476E-1],"split_indices":[15,7,8,0,0,0,0,0,0],"split_type":[0,0,0,0,0,0,0,0,0],"sum_hessian":[5.281587E2,3.5993228E2,1.682264E2,3.5882993E2,1.1023693E0,2.4569285E0,1.6576947E2,1.0042249E0,1.4527035E0],"tree_param":{"num_deleted":"0","num_feature":"17","num_nodes":"9","size_leaf_vector":"1"}},{"base_weights":[-1.8405104E-1,-1.114635E-1,1.6192079E0,3.0479616E-1,1.5845947E-1],"categories":[],"categories_nodes":[],"categories_segments":[],"categories_sizes":[],"default_left":[0,0,0,0,0],"id":7,"left_children":[1,-1,3,-1,-1],"loss_changes":[8.47903E2,0E0,3.67807E0,0E0,0E0],"parents":[2147483647,0,0,2,2],"right_children":[2,-1,4,-1,-1],"split_conditions":[2.2239482E0,-1.114635E-1,4.7192056E-2,3.0479616E-1,1.5845947E-1],"split_indices":[16,0,13,0,0],"split_type":[0,0,0,0,0],"sum_hessian":[5.0320496E2,3.3216885E2,1.7103612E2,1.9863509E0,1.6904976E2],"tree_param":{"num_deleted":"0","num_feature":"17","num_nodes":"5","size_leaf_vector":"1"}},{"base_weights":[-1.9862746E-1,-1.1020118E-1,1.5222572E-1],"categories":[],"categories_nodes":[],"categories_segments":[],"categories_sizes":[],"default_left":[0,0,0],"id":8,"left_children":[1,-1,-1],"loss_changes":[7.2172327E2,0E0,0E0],"parents":[2147483647,0,0],"right_children":[2,-1,-1],"split_conditions":[2.2239482E0,-1.1020118E-1,1.5222572E-1],"split_indices":[16,0,0],"split_type":[0,0,0],"sum_hessian":[4.6216507E2,3.0330414E2,1.5886093E2],"tree_param":{"num_deleted":"0","num_feature":"17","num_nodes":"3","size_leaf_vector":"1"}},{"base_weights":[-1.8718897E-1,-1.0907067E-1,1.4617938E0,2.5682762E-1,1.4261039E-1],"categories":[],"categories_nodes":[],"categories_segments":[],"categories_sizes":[],"default_left":[0,0,0,0,0],"id":9,"left_children":[1,-1,3,-1,-1],"loss_changes":[6.417476E2,0E0,2.360321E0,0E0,0E0],"parents":[2147483647,0,0,2,2],"right_children":[2,-1,4,-1,-1],"split_conditions":[2.2239482E0,-1.0907067E-1,2.2385104E0,2.5682762E-1,1.4261039E-1],"split_indices":[16,0,15,0,0],"split_type":[0,0,0,0,0],"sum_hessian":[4.2866614E2,2.7714838E2,1.5151778E2,2.5171974E0,1.4900058E2],"tree_param":{"num_deleted":"0","num_feature":"17","num_nodes":"5","size_leaf_vector":"1"}},{"base_weights":[-1.8452835E-1,-1.0805438E-1,1.3945872E-1],"categories":[],"categories_nodes":[],"categories_segments":[],"categories_sizes":[],"default_left":[0,0,0],"id":10,"left_children":[1,-1,-1],"loss_changes":[5.5657294E2,0E0,0E0],"parents":[2147483647,0,0],"right_children":[2,-1,-1],"split_conditions":[2.2239482E0,-1.0805438E-1,1.3945872E-1],"split_indices":[16,0,0],"split_type":[0,0,0],"sum_hessian":[3.9129724E2,2.4984624E2,1.4145102E2],"tree_param":{"num_deleted":"0","num_feature":"17","num_nodes":"3","size_leaf_vector":"1"}},{"base_weights":[-1.7313126E-1,-1.0715222E-1,1.3476612E-1],"categories":[],"categories_nodes":[],"categories_segments":[],"categories_sizes":[],"default_left":[0,0,0],"id":11,"left_children":[1,-1,-1],"loss_changes":[4.9803195E2,0E0,0E0],"parents":[2147483647,0,0],"right_children":[2,-1,-1],"split_conditions":[2.2239482E0,-1.0715222E-1,1.3476612E-1],"split_indices":[16,0,0],"split_type":[0,0,0],"sum_hessian":[3.6246353E2,2.2804433E2,1.344192E2],"tree_param":{"num_deleted":"0","num_feature":"17","num_nodes":"3","size_leaf_vector":"1"}},{"base_weights":[-1.930411E-1,-1.0262194E0,1.2649256E0,-1.03737034E-1,6.512918E-2,3.957315E-2,1.2746613E-1],"categories":[],"categories_nodes":[],"categories_segments":[],"categories_sizes":[],"default_left":[0,0,0,0,0,0,0],"id":12,"left_children":[1,3,5,-1,-1,-1,-1],"loss_changes":[4.0608054E2,4.6524963E0,5.248108E-1,0E0,0E0,0E0,0E0],"parents":[2147483647,0,0,1,1,2,2],"right_children":[2,4,6,-1,-1,-1,-1],"split_conditions":[4.7192056E-2,1.6076784E0,2.2385104E0,-1.03737034E-1,6.512918E-2,3.957315E-2,1.2746613E-1],"split_indices":[13,7,15,0,0,0,0],"split_type":[0,0,0,0,0,0,0],"sum_hessian":[3.322239E2,2.1159865E2,1.2062528E2,2.1058044E2,1.0182021E0,1.7974615E0,1.1882782E2],"tree_param":{"num_deleted":"0","num_feature":"17","num_nodes":"7","size_leaf_vector":"1"}},{"base_weights":[-1.8189326E-1,-1.0562086E-1,1.2661515E-1],"categories":[],"categories_nodes":[],"categories_segments":[],"categories_sizes":[],"default_left":[0,0,0],"id":13,"left_children":[1,-1,-1],"loss_changes":[3.905003E2,0E0,0E0],"parents":[2147483647,0,0],"right_children":[2,-1,-1],"split_conditions":[2.2239482E0,-1.0562086E-1,1.2661515E-1],"split_indices":[16,0,0],"split_type":[0,0,0],"sum_hessian":[3.063841E2,1.9120624E2,1.1517787E2],"tree_param":{"num_deleted":"0","num_feature":"17","num_nodes":"3","size_leaf_vector":"1"}},{"base_weights":[-1.8642616E-1,-1.0034606E0,1.2069478E-1,-1.01878166E-1,7.746506E-2],"categories":[],"categories_nodes":[],"categories_segments":[],"categories_sizes":[],"default_left":[0,0,0,0,0],"id":14,"left_children":[1,3,-1,-1,-1],"loss_changes":[3.2335245E2,5.6634674E0,0E0,0E0,0E0],"parents":[2147483647,0,0,1,1],"right_children":[2,4,-1,-1,-1],"split_conditions":[2.2385104E0,1.9875274E0,1.2069478E-1,-1.01878166E-1,7.746506E-2],"split_indices":[15,7,0,0,0],"split_type":[0,0,0,0,0],"sum_hessian":[2.8196866E2,1.7792084E2,1.0404783E2,1.7682428E2,1.0965605E0],"tree_param":{"num_deleted":"0","num_feature":"17","num_nodes":"5","size_leaf_vector":"1"}},{"base_weights":[-1.784335E-1,-1.043756E-1,1.21486686E-1],"categories":[],"categories_nodes":[],"categories_segments":[],"categories_sizes":[],"default_left":[0,0,0],"id":15,"left_children":[1,-1,-1],"loss_changes":[3.1280496E2,0E0,0E0],"parents":[2147483647,0,0],"right_children":[2,-1,-1],"split_conditions":[2.2239482E0,-1.043756E-1,1.21486686E-1],"split_indices":[16,0,0],"split_type":[0,0,0],"sum_hessian":[2.5739658E2,1.5893768E2,9.845889E1],"tree_param":{"num_deleted":"0","num_feature":"17","num_nodes":"3","size_leaf_vector":"1"}},{"base_weights":[-1.804611E-1,-1.03816584E-1,1.1876835E-1],"categories":[],"categories_nodes":[],"categories_segments":[],"categories_sizes":[],"default_left":[0,0,0],"id":16,"left_children":[1,-1,-1],"loss_changes":[2.7781326E2,0E0,0E0],"parents":[2147483647,0,0],"right_children":[2,-1,-1],"split_conditions":[2.2239482E0,-1.03816584E-1,1.1876835E-1],"split_indices":[16,0,0],"split_type":[0,0,0],"sum_hessian":[2.3469556E2,1.4440665E2,9.028891E1],"tree_param":{"num_deleted":"0","num_feature":"17","num_nodes":"3","size_leaf_vector":"1"}},{"base_weights":[-1.820287E-1,-1.03302255E-1,1.1807119E-1],"categories":[],"categories_nodes":[],"categories_segments":[],"categories_sizes":[],"default_left":[0,0,0],"id":17,"left_children":[1,-1,-1],"loss_changes":[2.4973845E2,0E0,0E0],"parents":[2147483647,0,0],"right_children":[2,-1,-1],"split_conditions":[2.2239482E0,-1.03302255E-1,1.1807119E-1],"split_indices":[16,0,0],"split_type":[0,0,0],"sum_hessian":[2.1329869E2,1.314523E2,8.1846375E1],"tree_param":{"num_deleted":"0","num_feature":"17","num_nodes":"3","size_leaf_vector":"1"}},{"base_weights":[-1.748843E-1,-1.02836184E-1,1.15269855E-1],"categories":[],"categories_nodes":[],"categories_segments":[],"categories_sizes":[],"default_left":[0,0,0],"id":18,"left_children":[1,-1,-1],"loss_changes":[2.265986E2,0E0,0E0],"parents":[2147483647,0,0],"right_children":[2,-1,-1],"split_conditions":[2.2239482E0,-1.02836184E-1,1.15269855E-1],"split_indices":[16,0,0],"split_type":[0,0,0],"sum_hessian":[1.9794162E2,1.20621666E2,7.731996E1],"tree_param":{"num_deleted":"0","num_feature":"17","num_nodes":"3","size_leaf_vector":"1"}},{"base_weights":[-1.5345368E-1,-1.0237517E-1,1.1495966E-1],"categories":[],"categories_nodes":[],"categories_segments":[],"categories_sizes":[],"default_left":[0,0,0],"id":19,"left_children":[1,-1,-1],"loss_changes":[2.0637114E2,0E0,0E0],"parents":[2147483647,0,0],"right_children":[2,-1,-1],"split_conditions":[2.2239482E0,-1.0237517E-1,1.1495966E-1],"split_indices":[16,0,0],"split_type":[0,0,0],"sum_hessian":[1.799406E2,1.080135E2,7.19271E1],"tree_param":{"num_deleted":"0","num_feature":"17","num_nodes":"3","size_leaf_vector":"1"}},{"base_weights":[-1.6797052E-1,-1.0197013E-1,1.1212226E-1],"categories":[],"categories_nodes":[],"categories_segments":[],"categories_sizes":[],"default_left":[0,0,0],"id":20,"left_children":[1,-1,-1],"loss_changes":[1.820913E2,0E0,0E0],"parents":[2147483647,0,0],"right_children":[2,-1,-1],"split_conditions":[2.2239482E0,-1.0197013E-1,1.1212226E-1],"split_indices":[16,0,0],"split_type":[0,0,0],"sum_hessian":[1.6379097E2,9.8755356E1,6.503562E1],"tree_param":{"num_deleted":"0","num_feature":"17","num_nodes":"3","size_leaf_vector":"1"}},{"base_weights":[-1.634475E-1,-1.0156744E-1,1.10779144E-1],"categories":[],"categories_nodes":[],"categories_segments":[],"categories_sizes":[],"default_left":[0,0,0],"id":21,"left_children":[1,-1,-1],"loss_changes":[1.6257358E2,0E0,0E0],"parents":[2147483647,0,0],"right_children":[2,-1,-1],"split_conditions":[2.2239482E0,-1.0156744E-1,1.10779144E-1],"split_indices":[16,0,0],"split_type":[0,0,0],"sum_hessian":[1.4802235E2,8.873575E1,5.92866E1],"tree_param":{"num_deleted":"0","num_feature":"17","num_nodes":"3","size_leaf_vector":"1"}},{"base_weights":[-1.7044231E-1,-1.01208426E-1,1.09956816E-1],"categories":[],"categories_nodes":[],"categories_segments":[],"categories_sizes":[],"default_left":[0,0,0],"id":22,"left_children":[1,-1,-1],"loss_changes":[1.463013E2,0E0,0E0],"parents":[2147483647,0,0],"right_children":[2,-1,-1],"split_conditions":[2.2239482E0,-1.01208426E-1,1.09956816E-1],"split_indices":[16,0,0],"split_type":[0,0,0],"sum_hessian":[1.3483054E2,8.1213234E1,5.3617302E1],"tree_param":{"num_deleted":"0","num_feature":"17","num_nodes":"3","size_leaf_vector":"1"}},{"base_weights":[-1.5671803E-1,-1.00846015E-1,1.0918553E-1],"categories":[],"categories_nodes":[],"categories_segments":[],"categories_sizes":[],"default_left":[0,0,0],"id":23,"left_children":[1,-1,-1],"loss_changes":[1.3395984E2,0E0,0E0],"parents":[2147483647,0,0],"right_children":[2,-1,-1],"split_conditions":[2.2239482E0,-1.00846015E-1,1.0918553E-1],"split_indices":[16,0,0],"split_type":[0,0,0],"sum_hessian":[1.2393036E2,7.378713E1,5.014323E1],"tree_param":{"num_deleted":"0","num_feature":"17","num_nodes":"3","size_leaf_vector":"1"}},{"base_weights":[-1.4713283E-1,-9.1300946E-1,1.0337476E0,-9.2267096E-1,-1.2902619E-2,2.8940236E-2,1.04630284E-1,-9.3157165E-2,-1.793511E-2],"categories":[],"categories_nodes":[],"categories_segments":[],"categories_sizes":[],"default_left":[0,0,0,0,0,0,0,0,0],"id":24,"left_children":[1,3,5,7,-1,-1,-1,-1,-1],"loss_changes":[1.040139E2,4.085846E-1,1.20586395E-1,2.8710938E-1,0E0,0E0,0E0,0E0,0E0],"parents":[2147483647,0,0,1,1,2,2,3,3],"right_children":[2,4,6,8,-1,-1,-1,-1,-1],"split_conditions":[2.2385104E0,1.1645215E0,-1.6895375E0,9.8042095E-1,-1.2902619E-2,2.8940236E-2,1.04630284E-1,-9.3157165E-2,-1.793511E-2],"split_indices":[15,7,0,10,0,0,0,0,0],"split_type":[0,0,0,0,0,0,0,0,0],"sum_hessian":[1.1296405E2,6.8660286E1,4.430376E1,6.76497E1,1.0105885E0,1.1338372E0,4.316992E1,6.659897E1,1.0507282E0],"tree_param":{"num_deleted":"0","num_feature":"17","num_nodes":"9","size_leaf_vector":"1"}},{"base_weights":[-1.6579668E-1,-9.3554014E-1,1.0269989E-1,-9.453801E-1,-1.6653022E-2,-9.546763E-2,-2.2760613E-2],"categories":[],"categories_nodes":[],"categories_segments":[],"categories_sizes":[],"default_left":[0,0,0,0,0,0,0],"id":25,"left_children":[1,3,-1,5,-1,-1,-1],"loss_changes":[9.7061356E1,3.2790756E-1,0E0,2.0383835E-1,0E0,0E0,0E0],"parents":[2147483647,0,0,1,1,3,3],"right_children":[2,4,-1,6,-1,-1,-1],"split_conditions":[4.7192056E-2,1.0575978E0,1.0269989E-1,8.2687795E-1,-1.6653022E-2,-9.546763E-2,-2.2760613E-2],"split_indices":[13,10,0,7,0,0,0],"split_type":[0,0,0,0,0,0,0],"sum_hessian":[1.03667984E2,6.3138603E1,4.0529385E1,6.211446E1,1.0241417E0,6.099445E1,1.1200128E0],"tree_param":{"num_deleted":"0","num_feature":"17","num_nodes":"7","size_leaf_vector":"1"}},{"base_weights":[-1.4596668E-1,-9.988808E-2,1.07886665E-1],"categories":[],"categories_nodes":[],"categories_segments":[],"categories_sizes":[],"default_left":[0,0,0],"id":26,"left_children":[1,-1,-1],"loss_changes":[1.0073669E2,0E0,0E0],"parents":[2147483647,0,0],"right_children":[2,-1,-1],"split_conditions":[2.2239482E0,-9.988808E-2,1.07886665E-1],"split_indices":[16,0,0],"split_type":[0,0,0],"sum_hessian":[9.439693E1,5.575579E1,3.8641132E1],"tree_param":{"num_deleted":"0","num_feature":"17","num_nodes":"3","size_leaf_vector":"1"}},{"base_weights":[-1.6369617E-1,-9.95967E-2,1.0580888E-1],"categories":[],"categories_nodes":[],"categories_segments":[],"categories_sizes":[],"default_left":[0,0,0],"id":27,"left_children":[1,-1,-1],"loss_changes":[9.03507E1,0E0,0E0],"parents":[2147483647,0,0],"right_children":[2,-1,-1],"split_conditions":[2.2239482E0,-9.95967E-2,1.0580888E-1],"split_indices":[16,0,0],"split_type":[0,0,0],"sum_hessian":[8.6816635E1,5.1749847E1,3.5066788E1],"tree_param":{"num_deleted":"0","num_feature":"17","num_nodes":"3","size_leaf_vector":"1"}},{"base_weights":[-1.5954928E-1,-9.923995E-2,1.0551591E-1],"categories":[],"categories_nodes":[],"categories_segments":[],"categories_sizes":[],"default_left":[0,0,0],"id":28,"left_children":[1,-1,-1],"loss_changes":[8.125559E1,0E0,0E0],"parents":[2147483647,0,0],"right_children":[2,-1,-1],"split_conditions":[2.2239482E0,-9.923995E-2,1.0551591E-1],"split_indices":[16,0,0],"split_type":[0,0,0],"sum_hessian":[7.82832E1,4.6549866E1,3.1733343E1],"tree_param":{"num_deleted":"0","num_feature":"17","num_nodes":"3","size_leaf_vector":"1"}},{"base_weights":[-1.5411904E-1,-8.983019E-1,9.906966E-2,-9.113256E-1,-1.7294768E-2,-1.8682992E-2,-9.246338E-2],"categories":[],"categories_nodes":[],"categories_segments":[],"categories_sizes":[],"default_left":[0,0,0,0,0,0,0],"id":29,"left_children":[1,3,-1,5,-1,-1,-1],"loss_changes":[6.2212273E1,2.5943375E-1,0E0,2.4313354E-1,0E0,0E0,0E0],"parents":[2147483647,0,0,1,1,3,3],"right_children":[2,4,-1,6,-1,-1,-1],"split_conditions":[4.7192056E-2,1.0379051E0,9.906966E-2,-1.1532644E0,-1.7294768E-2,-1.8682992E-2,-9.246338E-2],"split_indices":[13,7,0,11,0,0,0],"split_type":[0,0,0,0,0,0,0],"sum_hessian":[7.0978615E1,4.314664E1,2.783197E1,4.2133747E1,1.0128952E0,1.0312563E0,4.110249E1],"tree_param":{"num_deleted":"0","num_feature":"17","num_nodes":"7","size_leaf_vector":"1"}},{"base_weights":[-1.5584165E-1,-8.717428E-1,9.8351315E-2,-8.847375E-2,-1.7299032E-2],"categories":[],"categories_nodes":[],"categories_segments":[],"categories_sizes":[],"default_left":[0,0,0,0,0],"id":30,"left_children":[1,3,-1,-1,-1],"loss_changes":[5.5367374E1,2.2441673E-1,0E0,0E0,0E0],"parents":[2147483647,0,0,1,1],"right_children":[2,4,-1,-1,-1],"split_conditions":[2.2385104E0,1.1012132E0,9.8351315E-2,-8.847375E-2,-1.7299032E-2],"split_indices":[15,7,0,0,0],"split_type":[0,0,0,0,0],"sum_hessian":[6.582888E1,4.0571255E1,2.5257626E1,3.956922E1,1.0020355E0],"tree_param":{"num_deleted":"0","num_feature":"17","num_nodes":"5","size_leaf_vector":"1"}},{"base_weights":[-1.5230194E-1,-8.5873157E-1,9.773366E-2,-2.5937492E-1,-8.925807E-2,-4.845364E-2,8.6426465E-3],"categories":[],"categories_nodes":[],"categories_segments":[],"categories_sizes":[],"default_left":[0,0,0,0,0,0,0],"id":31,"left_children":[1,3,-1,5,-1,-1,-1],"loss_changes":[4.9815662E1,5.453434E-1,0E0,3.1101066E-1,0E0,0E0,0E0],"parents":[2147483647,0,0,1,1,3,3],"right_children":[2,4,-1,6,-1,-1,-1],"split_conditions":[2.2385104E0,-1.1235315E0,9.773366E-2,-8.3453394E-2,-8.925807E-2,-4.845364E-2,8.6426465E-3],"split_indices":[15,5,0,0,0,0,0],"split_type":[0,0,0,0,0,0,0],"sum_hessian":[6.0373146E1,3.7292046E1,2.30811E1,2.4565878E0,3.4835457E1,1.2448382E0,1.2117494E0],"tree_param":{"num_deleted":"0","num_feature":"17","num_nodes":"7","size_leaf_vector":"1"}},{"base_weights":[-1.3071245E-1,-9.7974494E-2,1.0639232E-1],"categories":[],"categories_nodes":[],"categories_segments":[],"categories_sizes":[],"default_left":[0,0,0],"id":32,"left_children":[1,-1,-1],"loss_changes":[5.8378212E1,0E0,0E0],"parents":[2147483647,0,0],"right_children":[2,-1,-1],"split_conditions":[2.2239482E0,-9.7974494E-2,1.0639232E-1],"split_indices":[16,0,0],"split_type":[0,0,0],"sum_hessian":[5.5528362E1,3.256451E1,2.2963852E1],"tree_param":{"num_deleted":"0","num_feature":"17","num_nodes":"3","size_leaf_vector":"1"}},{"base_weights":[-1.315871E-1,-9.759881E-2,1.0537305E-1],"categories":[],"categories_nodes":[],"categories_segments":[],"categories_sizes":[],"default_left":[0,0,0],"id":33,"left_children":[1,-1,-1],"loss_changes":[5.271512E1,0E0,0E0],"parents":[2147483647,0,0],"right_children":[2,-1,-1],"split_conditions":[2.2239482E0,-9.759881E-2,1.0537305E-1],"split_indices":[16,0,0],"split_type":[0,0,0],"sum_hessian":[5.0641068E1,2.9676567E1,2.0964502E1],"tree_param":{"num_deleted":"0","num_feature":"17","num_nodes":"3","size_leaf_vector":"1"}},{"base_weights":[-1.2362642E-1,-9.717122E-2,1.044135E-1],"categories":[],"categories_nodes":[],"categories_segments":[],"categories_sizes":[],"default_left":[0,0,0],"id":34,"left_children":[1,-1,-1],"loss_changes":[4.749881E1,0E0,0E0],"parents":[2147483647,0,0],"right_children":[2,-1,-1],"split_conditions":[2.2239482E0,-9.717122E-2,1.044135E-1],"split_indices":[16,0,0],"split_type":[0,0,0],"sum_hessian":[4.5936592E1,2.6707891E1,1.92287E1],"tree_param":{"num_deleted":"0","num_feature":"17","num_nodes":"3","size_leaf_vector":"1"}},{"base_weights":[-1.4824435E-1,-9.683114E-2,1.0271835E-1],"categories":[],"categories_nodes":[],"categories_segments":[],"categories_sizes":[],"default_left":[0,0,0],"id":35,"left_children":[1,-1,-1],"loss_changes":[4.243102E1,0E0,0E0],"parents":[2147483647,0,0],"right_children":[2,-1,-1],"split_conditions":[2.2239482E0,-9.683114E-2,1.0271835E-1],"split_indices":[16,0,0],"split_type":[0,0,0],"sum_hessian":[4.198694E1,2.483581E1,1.7151129E1],"tree_param":{"num_deleted":"0","num_feature":"17","num_nodes":"3","size_leaf_vector":"1"}},{"base_weights":[-1.2281868E-1,-9.634309E-2,1.0264062E-1],"categories":[],"categories_nodes":[],"categories_segments":[],"categories_sizes":[],"default_left":[0,0,0],"id":36,"left_children":[1,-1,-1],"loss_changes":[3.906229E1,0E0,0E0],"parents":[2147483647,0,0],"right_children":[2,-1,-1],"split_conditions":[2.2239482E0,-9.634309E-2,1.0264062E-1],"split_indices":[16,0,0],"split_type":[0,0,0],"sum_hessian":[3.8411335E1,2.2277729E1,1.6133604E1],"tree_param":{"num_deleted":"0","num_feature":"17","num_nodes":"3","size_leaf_vector":"1"}},{"base_weights":[-1.2724587E-1,-7.693577E-1,9.256332E-2,-3.527656E-1,-8.663597E-2,2.6171505E-2,-7.47225E-2],"categories":[],"categories_nodes":[],"categories_segments":[],"categories_sizes":[],"default_left":[0,0,0,0,0,0,0],"id":37,"left_children":[1,3,-1,5,-1,-1,-1],"loss_changes":[2.4747469E1,6.088562E-1,0E0,1.6404154E0,0E0,0E0,0E0],"parents":[2147483647,0,0,1,1,3,3],"right_children":[2,4,-1,6,-1,-1,-1],"split_conditions":[4.7192056E-2,-7.8456295E-1,9.256332E-2,-1.032208E0,-8.663597E-2,2.6171505E-2,-7.47225E-2],"split_indices":[13,3,0,11,0,0,0],"split_type":[0,0,0,0,0,0,0],"sum_hessian":[3.4551743E1,2.1629808E1,1.2921933E1,4.960928E0,1.6668879E1,2.0711133E0,2.8898149E0],"tree_param":{"num_deleted":"0","num_feature":"17","num_nodes":"7","size_leaf_vector":"1"}},{"base_weights":[-1.22709036E-1,-9.546588E-2,1.0176202E-1],"categories":[],"categories_nodes":[],"categories_segments":[],"categories_sizes":[],"default_left":[0,0,0],"id":38,"left_children":[1,-1,-1],"loss_changes":[3.2484398E1,0E0,0E0],"parents":[2147483647,0,0],"right_children":[2,-1,-1],"split_conditions":[2.2239482E0,-9.546588E-2,1.0176202E-1],"split_indices":[16,0,0],"split_type":[0,0,0],"sum_hessian":[3.2217068E1,1.8721354E1,1.3495713E1],"tree_param":{"num_deleted":"0","num_feature":"17","num_nodes":"3","size_leaf_vector":"1"}},{"base_weights":[-1.1370365E-1,-7.0637673E-1,9.075037E-2,-3.3923498E-1,-8.143923E-2,-6.54388E-2,2.6092408E-2],"categories":[],"categories_nodes":[],"categories_segments":[],"categories_sizes":[],"default_left":[0,0,0,0,0,0,0],"id":39,"left_children":[1,3,-1,5,-1,-1,-1],"loss_changes":[1.8702303E1,4.9485588E-1,0E0,1.3309941E0,0E0,0E0,0E0],"parents":[2147483647,0,0,1,1,3,3],"right_children":[2,4,-1,6,-1,-1,-1],"split_conditions":[2.2385104E0,-1.032208E0,9.075037E-2,-9.4008297E-1,-8.143923E-2,-6.54388E-2,2.6092408E-2],"split_indices":[15,11,0,8,0,0,0],"split_type":[0,0,0,0,0,0,0],"sum_hessian":[2.8841389E1,1.8444904E1,1.0396485E1,5.1342726E0,1.3310631E1,3.307234E0,1.8270388E0],"tree_param":{"num_deleted":"0","num_feature":"17","num_nodes":"7","size_leaf_vector":"1"}},{"base_weights":[-1.554818E-1,-7.557087E-1,8.891383E-2,-4.214988E-1,-8.4161095E-2,-6.33671E-2,7.942478E-3],"categories":[],"categories_nodes":[],"categories_segments":[],"categories_sizes":[],"default_left":[0,0,0,0,0,0,0],"id":40,"left_children":[1,3,-1,5,-1,-1,-1],"loss_changes":[1.8028101E1,1.6548443E-1,0E0,6.570345E-1,0E0,0E0,0E0],"parents":[2147483647,0,0,1,1,3,3],"right_children":[2,4,-1,6,-1,-1,-1],"split_conditions":[2.2385104E0,-1.032208E0,8.891383E-2,-9.4008297E-1,-8.4161095E-2,-6.33671E-2,7.942478E-3],"split_indices":[15,11,0,8,0,0,0],"split_type":[0,0,0,0,0,0,0],"sum_hessian":[2.6680893E1,1.712032E1,9.560572E0,4.7084455E0,1.2411875E1,3.1213536E0,1.587092E0],"tree_param":{"num_deleted":"0","num_feature":"17","num_nodes":"7","size_leaf_vector":"1"}},{"base_weights":[-1.4038937E-1,-9.41245E-2,9.854947E-2],"categories":[],"categories_nodes":[],"categories_segments":[],"categories_sizes":[],"default_left":[0,0,0],"id":41,"left_children":[1,-1,-1],"loss_changes":[2.4622606E1,0E0,0E0],"parents":[2147483647,0,0],"right_children":[2,-1,-1],"split_conditions":[2.2239482E0,-9.41245E-2,9.854947E-2],"split_indices":[16,0,0],"split_type":[0,0,0],"sum_hessian":[2.5279015E1,1.4867539E1,1.0411476E1],"tree_param":{"num_deleted":"0","num_feature":"17","num_nodes":"3","size_leaf_vector":"1"}},{"base_weights":[-1.4498119E-1,-9.345019E-2,9.7191066E-2],"categories":[],"categories_nodes":[],"categories_segments":[],"categories_sizes":[],"default_left":[0,0,0],"id":42,"left_children":[1,-1,-1],"loss_changes":[2.1823904E1,0E0,0E0],"parents":[2147483647,0,0],"right_children":[2,-1,-1],"split_conditions":[2.2239482E0,-9.345019E-2,9.7191066E-2],"split_indices":[16,0,0],"split_type":[0,0,0],"sum_hessian":[2.2719025E1,1.3405851E1,9.313173E0],"tree_param":{"num_deleted":"0","num_feature":"17","num_nodes":"3","size_leaf_vector":"1"}},{"base_weights":[-1.1648891E-1,-9.279421E-2,9.8688334E-2],"categories":[],"categories_nodes":[],"categories_segments":[],"categories_sizes":[],"default_left":[0,0,0],"id":43,"left_children":[1,-1,-1],"loss_changes":[2.0665825E1,0E0,0E0],"parents":[2147483647,0,0],"right_children":[2,-1,-1],"split_conditions":[2.2239482E0,-9.279421E-2,9.8688334E-2],"split_indices":[16,0,0],"split_type":[0,0,0],"sum_hessian":[2.1058844E1,1.2226271E1,8.832574E0],"tree_param":{"num_deleted":"0","num_feature":"17","num_nodes":"3","size_leaf_vector":"1"}},{"base_weights":[-1.07588805E-1,-9.194456E-2,9.649466E-2],"categories":[],"categories_nodes":[],"categories_segments":[],"categories_sizes":[],"default_left":[0,0,0],"id":44,"left_children":[1,-1,-1],"loss_changes":[1.839073E1,0E0,0E0],"parents":[2147483647,0,0],"right_children":[2,-1,-1],"split_conditions":[2.2239482E0,-9.194456E-2,9.649466E-2],"split_indices":[16,0,0],"split_type":[0,0,0],"sum_hessian":[1.9101763E1,1.095335E1,8.148414E0],"tree_param":{"num_deleted":"0","num_feature":"17","num_nodes":"3","size_leaf_vector":"1"}},{"base_weights":[-8.2944445E-2,-5.8590305E-1,8.390214E-2,-1.2452817E-1,-7.225182E-1,2.3267835E-2,-5.47222E-2,-3.5174388E-1,-8.496499E-2,-6.1928947E-2,2.337685E-2],"categories":[],"categories_nodes":[],"categories_segments":[],"categories_sizes":[],"default_left":[0,0,0,0,0,0,0,0,0,0,0],"id":45,"left_children":[1,3,-1,5,7,-1,-1,9,-1,-1,-1],"loss_changes":[9.309741E0,7.226834E-1,0E0,7.544973E-1,1.60223E-1,0E0,0E0,8.0164075E-1,0E0,0E0,0E0],"parents":[2147483647,0,0,1,1,3,3,4,4,7,7],"right_children":[2,4,-1,6,8,-1,-1,10,-1,-1,-1],"split_conditions":[4.7192056E-2,-7.8456295E-1,8.390214E-2,-8.718237E-1,-7.0384276E-1,2.3267835E-2,-5.47222E-2,-8.9279383E-1,-8.496499E-2,-6.1928947E-2,2.337685E-2],"split_indices":[13,3,0,10,0,0,0,0,0,0,0],"split_type":[0,0,0,0,0,0,0,0,0,0,0],"sum_hessian":[1.8016504E1,1.1893026E1,6.123478E0,3.15375E0,8.739277E0,1.952924E0,1.2008259E0,3.193202E0,5.5460744E0,2.152119E0,1.041083E0],"tree_param":{"num_deleted":"0","num_feature":"17","num_nodes":"11","size_leaf_vector":"1"}},{"base_weights":[-1.4086446E-1,-9.0813585E-2,9.2266954E-2],"categories":[],"categories_nodes":[],"categories_segments":[],"categories_sizes":[],"default_left":[0,0,0],"id":46,"left_children":[1,-1,-1],"loss_changes":[1.4972549E1,0E0,0E0],"parents":[2147483647,0,0],"right_children":[2,-1,-1],"split_conditions":[2.2239482E0,-9.0813585E-2,9.2266954E-2],"split_indices":[16,0,0],"split_type":[0,0,0],"sum_hessian":[1.6321457E1,9.566184E0,6.755272E0],"tree_param":{"num_deleted":"0","num_feature":"17","num_nodes":"3","size_leaf_vector":"1"}},{"base_weights":[-1.11165255E-1,-9.002892E-2,9.2869006E-2],"categories":[],"categories_nodes":[],"categories_segments":[],"categories_sizes":[],"default_left":[0,0,0],"id":47,"left_children":[1,-1,-1],"loss_changes":[1.4222028E1,0E0,0E0],"parents":[2147483647,0,0],"right_children":[2,-1,-1],"split_conditions":[2.2239482E0,-9.002892E-2,9.2869006E-2],"split_indices":[16,0,0],"split_type":[0,0,0],"sum_hessian":[1.53128805E1,8.782355E0,6.5305247E0],"tree_param":{"num_deleted":"0","num_feature":"17","num_nodes":"3","size_leaf_vector":"1"}},{"base_weights":[-1.3966994E-1,-6.579742E-1,7.9633914E-2,-2.2918697E-1,-7.551295E-2,2.5450826E-2,-5.6071617E-2],"categories":[],"categories_nodes":[],"categories_segments":[],"categories_sizes":[],"default_left":[0,0,0,0,0,0,0],"id":48,"left_children":[1,3,-1,5,-1,-1,-1],"loss_changes":[7.713756E0,2.4710321E-1,0E0,6.7171496E-1,0E0,0E0,0E0],"parents":[2147483647,0,0,1,1,3,3],"right_children":[2,4,-1,6,-1,-1,-1],"split_conditions":[2.2385104E0,-7.8456295E-1,7.9633914E-2,-1.0564193E0,-7.551295E-2,2.5450826E-2,-5.6071617E-2],"split_indices":[15,3,0,11,0,0,0],"split_type":[0,0,0,0,0,0,0],"sum_hessian":[1.38201E1,9.085919E0,4.7341805E0,2.2988968E0,6.7870226E0,1.0293758E0,1.2695209E0],"tree_param":{"num_deleted":"0","num_feature":"17","num_nodes":"7","size_leaf_vector":"1"}},{"base_weights":[-1.0766314E-1,-8.850499E-2,9.134957E-2],"categories":[],"categories_nodes":[],"categories_segments":[],"categories_sizes":[],"default_left":[0,0,0],"id":49,"left_children":[1,-1,-1],"loss_changes":[1.2034258E1,0E0,0E0],"parents":[2147483647,0,0],"right_children":[2,-1,-1],"split_conditions":[2.2239482E0,-8.850499E-2,9.134957E-2],"split_indices":[16,0,0],"split_type":[0,0,0],"sum_hessian":[1.314118E1,7.536835E0,5.6043453E0],"tree_param":{"num_deleted":"0","num_feature":"17","num_nodes":"3","size_leaf_vector":"1"}},{"base_weights":[-6.714589E-2,-8.7406926E-2,9.1706686E-2],"categories":[],"categories_nodes":[],"categories_segments":[],"categories_sizes":[],"default_left":[0,0,0],"id":50,"left_children":[1,-1,-1],"loss_changes":[1.136577E1,0E0,0E0],"parents":[2147483647,0,0],"right_children":[2,-1,-1],"split_conditions":[2.2239482E0,-8.7406926E-2,9.1706686E-2],"split_indices":[16,0,0],"split_type":[0,0,0],"sum_hessian":[1.2301939E1,6.8212957E0,5.4806433E0],"tree_param":{"num_deleted":"0","num_feature":"17","num_nodes":"3","size_leaf_vector":"1"}},{"base_weights":[-8.162384E-2,-5.288835E-1,7.605285E-2,-2.6768547E-1,-7.519466E-2,-6.14854E-2,1.0227407E-1,-9.182692E-3,2.8929988E-2],"categories":[],"categories_nodes":[],"categories_segments":[],"categories_sizes":[],"default_left":[0,0,0,0,0,0,0,0,0],"id":51,"left_children":[1,3,-1,5,-1,-1,7,-1,-1],"loss_changes":[4.9406304E0,2.9159045E-1,0E0,7.6279366E-1,0E0,0E0,1.5345822E-1,0E0,0E0],"parents":[2147483647,0,0,1,1,3,3,6,6],"right_children":[2,4,-1,6,-1,-1,8,-1,-1],"split_conditions":[4.7192056E-2,-1.5745923E-3,7.605285E-2,-7.195887E-1,-7.519466E-2,-6.14854E-2,-1.653322E-1,-9.182692E-3,2.8929988E-2],"split_indices":[13,0,0,0,0,0,0,0,0],"split_type":[0,0,0,0,0,0,0,0,0],"sum_hessian":[1.1049037E1,7.459401E0,3.5896358E0,4.449388E0,3.0100129E0,1.9539038E0,2.4954844E0,1.474362E0,1.0211222E0],"tree_param":{"num_deleted":"0","num_feature":"17","num_nodes":"9","size_leaf_vector":"1"}},{"base_weights":[-8.4109165E-2,-5.0522614E-1,7.35477E-2,-6.25256E-2,-6.40248E-1,2.1347037E-2,-3.0532062E-2,-2.5699976E-1,-7.640779E-2,-5.0475515E-2,1.1777024E-2],"categories":[],"categories_nodes":[],"categories_segments":[],"categories_sizes":[],"default_left":[0,0,0,0,0,0,0,0,0,0,0],"id":52,"left_children":[1,3,-1,5,7,-1,-1,9,-1,-1,-1],"loss_changes":[4.396936E0,4.5592093E-1,0E0,2.693829E-1,1.0022879E-1,0E0,0E0,3.410653E-1,0E0,0E0,0E0],"parents":[2147483647,0,0,1,1,3,3,4,4,7,7],"right_children":[2,4,-1,6,8,-1,-1,10,-1,-1,-1],"split_conditions":[2.2385104E0,-7.8456295E-1,7.35477E-2,-1.0079967E0,-7.0384276E-1,2.1347037E-2,-3.0532062E-2,-1.0565515E0,-7.640779E-2,-5.0475515E-2,1.1777024E-2],"split_indices":[15,3,0,11,0,0,0,0,0,0,0],"split_type":[0,0,0,0,0,0,0,0,0,0,0],"sum_hessian":[1.0662904E1,7.297095E0,3.365809E0,2.0473757E0,5.249719E0,1.0147003E0,1.0326755E0,2.0330236E0,3.2166953E0,1.015109E0,1.0179147E0],"tree_param":{"num_deleted":"0","num_feature":"17","num_nodes":"11","size_leaf_vector":"1"}},{"base_weights":[-8.802877E-2,-8.526643E-2,8.802313E-2],"categories":[],"categories_nodes":[],"categories_segments":[],"categories_sizes":[],"default_left":[0,0,0],"id":53,"left_children":[1,-1,-1],"loss_changes":[8.976923E0,0E0,0E0],"parents":[2147483647,0,0],"right_children":[2,-1,-1],"split_conditions":[2.2239482E0,-8.526643E-2,8.802313E-2],"split_indices":[16,0,0],"split_type":[0,0,0],"sum_hessian":[1.0111235E1,5.7163863E0,4.3948483E0],"tree_param":{"num_deleted":"0","num_feature":"17","num_nodes":"3","size_leaf_vector":"1"}},{"base_weights":[-9.027789E-2,-8.413975E-2,8.620217E-2],"categories":[],"categories_nodes":[],"categories_segments":[],"categories_sizes":[],"default_left":[0,0,0],"id":54,"left_children":[1,-1,-1],"loss_changes":[8.069572E0,0E0,0E0],"parents":[2147483647,0,0],"right_children":[2,-1,-1],"split_conditions":[2.2239482E0,-8.413975E-2,8.620217E-2],"split_indices":[16,0,0],"split_type":[0,0,0],"sum_hessian":[9.26753E0,5.2461348E0,4.021395E0],"tree_param":{"num_deleted":"0","num_feature":"17","num_nodes":"3","size_leaf_vector":"1"}},{"base_weights":[-1.4664805E-1,-8.281477E-2,8.047131E-2],"categories":[],"categories_nodes":[],"categories_segments":[],"categories_sizes":[],"default_left":[0,0,0],"id":55,"left_children":[1,-1,-1],"loss_changes":[6.543469E0,0E0,0E0],"parents":[2147483647,0,0],"right_children":[2,-1,-1],"split_conditions":[2.2239482E0,-8.281477E-2,8.047131E-2],"split_indices":[16,0,0],"split_type":[0,0,0],"sum_hessian":[8.06459E0,4.774168E0,3.2904224E0],"tree_param":{"num_deleted":"0","num_feature":"17","num_nodes":"3","size_leaf_vector":"1"}},{"base_weights":[-1.5017658E-1,-8.166373E-2,7.867117E-2],"categories":[],"categories_nodes":[],"categories_segments":[],"categories_sizes":[],"default_left":[0,0,0],"id":56,"left_children":[1,-1,-1],"loss_changes":[5.910145E0,0E0,0E0],"parents":[2147483647,0,0],"right_children":[2,-1,-1],"split_conditions":[2.2239482E0,-8.166373E-2,7.867117E-2],"split_indices":[16,0,0],"split_type":[0,0,0],"sum_hessian":[7.4364085E0,4.420332E0,3.0160763E0],"tree_param":{"num_deleted":"0","num_feature":"17","num_nodes":"3","size_leaf_vector":"1"}},{"base_weights":[-1.5687919E-1,-8.036672E-2,7.599958E-2],"categories":[],"categories_nodes":[],"categories_segments":[],"categories_sizes":[],"default_left":[0,0,0],"id":57,"left_children":[1,-1,-1],"loss_changes":[5.241896E0,0E0,0E0],"parents":[2147483647,0,0],"right_children":[2,-1,-1],"split_conditions":[2.2239482E0,-8.036672E-2,7.599958E-2],"split_indices":[16,0,0],"split_type":[0,0,0],"sum_hessian":[6.8093204E0,4.0651364E0,2.7441845E0],"tree_param":{"num_deleted":"0","num_feature":"17","num_nodes":"3","size_leaf_vector":"1"}},{"base_weights":[-8.839353E-2,-7.88614E-2,7.816109E-2],"categories":[],"categories_nodes":[],"categories_segments":[],"categories_sizes":[],"default_left":[0,0,0],"id":58,"left_children":[1,-1,-1],"loss_changes":[5.2460566E0,0E0,0E0],"parents":[2147483647,0,0],"right_children":[2,-1,-1],"split_conditions":[2.2239482E0,-7.88614E-2,7.816109E-2],"split_indices":[16,0,0],"split_type":[0,0,0],"sum_hessian":[6.599649E0,3.708459E0,2.8911903E0],"tree_param":{"num_deleted":"0","num_feature":"17","num_nodes":"3","size_leaf_vector":"1"}},{"base_weights":[-6.402007E-2,-7.7739336E-2,7.812988E-2],"categories":[],"categories_nodes":[],"categories_segments":[],"categories_sizes":[],"default_left":[0,0,0],"id":59,"left_children":[1,-1,-1],"loss_changes":[5.024322E0,0E0,0E0],"parents":[2147483647,0,0],"right_children":[2,-1,-1],"split_conditions":[2.2239482E0,-7.7739336E-2,7.812988E-2],"split_indices":[16,0,0],"split_type":[0,0,0],"sum_hessian":[6.324613E0,3.4735792E0,2.8510342E0],"tree_param":{"num_deleted":"0","num_feature":"17","num_nodes":"3","size_leaf_vector":"1"}},{"base_weights":[-6.196781E-2,-7.644614E-2,7.6498166E-2],"categories":[],"categories_nodes":[],"categories_segments":[],"categories_sizes":[],"default_left":[0,0,0],"id":60,"left_children":[1,-1,-1],"loss_changes":[4.592719E0,0E0,0E0],"parents":[2147483647,0,0],"right_children":[2,-1,-1],"split_conditions":[2.2239482E0,-7.644614E-2,7.6498166E-2],"split_indices":[16,0,0],"split_type":[0,0,0],"sum_hessian":[5.8991833E0,3.2304664E0,2.668717E0],"tree_param":{"num_deleted":"0","num_feature":"17","num_nodes":"3","size_leaf_vector":"1"}},{"base_weights":[-1.09763324E-1,-5.00803E-1,5.959807E-2,1.4858226E-3,-6.972726E-2],"categories":[],"categories_nodes":[],"categories_segments":[],"categories_sizes":[],"default_left":[0,0,0,0,0],"id":61,"left_children":[1,3,-1,-1,-1],"loss_changes":[2.0058208E0,4.6872377E-1,0E0,0E0,0E0],"parents":[2147483647,0,0,1,1],"right_children":[2,4,-1,-1,-1],"split_conditions":[2.2385104E0,-7.8456295E-1,5.959807E-2,1.4858226E-3,-6.972726E-2],"split_indices":[15,3,0,0,0],"split_type":[0,0,0,0,0],"sum_hessian":[5.186642E0,3.5242891E0,1.6623532E0,1.2273402E0,2.296949E0],"tree_param":{"num_deleted":"0","num_feature":"17","num_nodes":"5","size_leaf_vector":"1"}},{"base_weights":[-6.746428E-2,-7.37349E-2,7.2713874E-2],"categories":[],"categories_nodes":[],"categories_segments":[],"categories_sizes":[],"default_left":[0,0,0],"id":62,"left_children":[1,-1,-1],"loss_changes":[3.7735403E0,0E0,0E0],"parents":[2147483647,0,0],"right_children":[2,-1,-1],"split_conditions":[2.2239482E0,-7.37349E-2,7.2713874E-2],"split_indices":[16,0,0],"split_type":[0,0,0],"sum_hessian":[5.0819683E0,2.7964733E0,2.2854948E0],"tree_param":{"num_deleted":"0","num_feature":"17","num_nodes":"3","size_leaf_vector":"1"}},{"base_weights":[-2.7365817E-2,-7.241564E-2,7.362958E-2],"categories":[],"categories_nodes":[],"categories_segments":[],"categories_sizes":[],"default_left":[0,0,0],"id":63,"left_children":[1,-1,-1],"loss_changes":[3.7001636E0,0E0,0E0],"parents":[2147483647,0,0],"right_children":[2,-1,-1],"split_conditions":[2.2239482E0,-7.241564E-2,7.362958E-2],"split_indices":[16,0,0],"split_type":[0,0,0],"sum_hessian":[4.951697E0,2.6162624E0,2.3354347E0],"tree_param":{"num_deleted":"0","num_feature":"17","num_nodes":"3","size_leaf_vector":"1"}},{"base_weights":[-3.9332718E-2,-3.6410645E-2,5.5518776E-2],"categories":[],"categories_nodes":[],"categories_segments":[],"categories_sizes":[],"default_left":[0,0,0],"id":64,"left_children":[1,-1,-1],"loss_changes":[1.2702383E0,0E0,0E0],"parents":[2147483647,0,0],"right_children":[2,-1,-1],"split_conditions":[4.7192056E-2,-3.6410645E-2,5.5518776E-2],"split_indices":[13,0,0],"split_type":[0,0,0],"sum_hessian":[4.531725E0,3.1813726E0,1.3503525E0],"tree_param":{"num_deleted":"0","num_feature":"17","num_nodes":"3","size_leaf_vector":"1"}},{"base_weights":[-5.303323E-2,-3.612515E-1,5.3358227E-2,-1.1936799E-2,-5.3137105E-2],"categories":[],"categories_nodes":[],"categories_segments":[],"categories_sizes":[],"default_left":[0,0,0,0,0],"id":65,"left_children":[1,3,-1,-1,-1],"loss_changes":[1.1661316E0,1.063326E-1,0E0,0E0,0E0],"parents":[2147483647,0,0,1,1],"right_children":[2,4,-1,-1,-1],"split_conditions":[4.7192056E-2,-1.5745923E-3,5.3358227E-2,-1.1936799E-2,-5.3137105E-2],"split_indices":[13,0,0,0,0],"split_type":[0,0,0,0,0],"sum_hessian":[4.3835406E0,3.1255155E0,1.258025E0,1.9931864E0,1.1323291E0],"tree_param":{"num_deleted":"0","num_feature":"17","num_nodes":"5","size_leaf_vector":"1"}},{"base_weights":[-2.6420252E-2,-3.1190392E-1,5.2241374E-2,-8.015284E-3,-5.1201243E-2],"categories":[],"categories_nodes":[],"categories_segments":[],"categories_sizes":[],"default_left":[0,0,0,0,0],"id":66,"left_children":[1,3,-1,-1,-1],"loss_changes":[1.0051451E0,1.5197903E-1,0E0,0E0,0E0],"parents":[2147483647,0,0,1,1],"right_children":[2,4,-1,-1,-1],"split_conditions":[4.7192056E-2,-1.5745923E-3,5.2241374E-2,-8.015284E-3,-5.1201243E-2],"split_indices":[13,0,0,0,0],"split_type":[0,0,0,0,0],"sum_hessian":[4.375193E0,3.1620867E0,1.2131065E0,2.1141636E0,1.0479232E0],"tree_param":{"num_deleted":"0","num_feature":"17","num_nodes":"5","size_leaf_vector":"1"}},{"base_weights":[-5.487451E-2,-6.925353E-2,6.861304E-2],"categories":[],"categories_nodes":[],"categories_segments":[],"categories_sizes":[],"default_left":[0,0,0],"id":67,"left_children":[1,-1,-1],"loss_changes":[2.8917797E0,0E0,0E0],"parents":[2147483647,0,0],"right_children":[2,-1,-1],"split_conditions":[2.2239482E0,-6.925353E-2,6.861304E-2],"split_indices":[16,0,0],"split_type":[0,0,0],"sum_hessian":[4.1144137E0,2.246571E0,1.8678427E0],"tree_param":{"num_deleted":"0","num_feature":"17","num_nodes":"3","size_leaf_vector":"1"}},{"base_weights":[-2.0645402E-2,-6.75069E-2,6.855989E-2],"categories":[],"categories_nodes":[],"categories_segments":[],"categories_sizes":[],"default_left":[0,0,0],"id":68,"left_children":[1,-1,-1],"loss_changes":[2.7503974E0,0E0,0E0],"parents":[2147483647,0,0],"right_children":[2,-1,-1],"split_conditions":[2.2239482E0,-6.75069E-2,6.855989E-2],"split_indices":[16,0,0],"split_type":[0,0,0],"sum_hessian":[3.949492E0,2.0728655E0,1.8766266E0],"tree_param":{"num_deleted":"0","num_feature":"17","num_nodes":"3","size_leaf_vector":"1"}},{"base_weights":[-3.77044E-2,-6.595226E-2,6.554142E-2],"categories":[],"categories_nodes":[],"categories_segments":[],"categories_sizes":[],"default_left":[0,0,0],"id":69,"left_children":[1,-1,-1],"loss_changes":[2.4228609E0,0E0,0E0],"parents":[2147483647,0,0],"right_children":[2,-1,-1],"split_conditions":[2.2239482E0,-6.595226E-2,6.554142E-2],"split_indices":[16,0,0],"split_type":[0,0,0],"sum_hessian":[3.618631E0,1.9329723E0,1.6856585E0],"tree_param":{"num_deleted":"0","num_feature":"17","num_nodes":"3","size_leaf_vector":"1"}},{"base_weights":[-1.2297273E-2,-6.4735584E-2,6.591037E-2],"categories":[],"categories_nodes":[],"categories_segments":[],"categories_sizes":[],"default_left":[0,0,0],"id":70,"left_children":[1,-1,-1],"loss_changes":[2.3579257E0,0E0,0E0],"parents":[2147483647,0,0],"right_children":[2,-1,-1],"split_conditions":[2.2239482E0,-6.4735584E-2,6.591037E-2],"split_indices":[16,0,0],"split_type":[0,0,0],"sum_hessian":[3.5294242E0,1.8322066E0,1.6972175E0],"tree_param":{"num_deleted":"0","num_feature":"17","num_nodes":"3","size_leaf_vector":"1"}},{"base_weights":[-3.9710138E-2,-6.290743E-2,6.1977953E-2],"categories":[],"categories_nodes":[],"categories_segments":[],"categories_sizes":[],"default_left":[0,0,0],"id":71,"left_children":[1,-1,-1],"loss_changes":[2.006906E0,0E0,0E0],"parents":[2147483647,0,0],"right_children":[2,-1,-1],"split_conditions":[2.2239482E0,-6.290743E-2,6.1977953E-2],"split_indices":[16,0,0],"split_type":[0,0,0],"sum_hessian":[3.1602874E0,1.6932265E0,1.467061E0],"tree_param":{"num_deleted":"0","num_feature":"17","num_nodes":"3","size_leaf_vector":"1"}},{"base_weights":[-7.4502476E-2,-6.1849006E-2,5.815767E-2],"categories":[],"categories_nodes":[],"categories_segments":[],"categories_sizes":[],"default_left":[0,0,0],"id":72,"left_children":[1,-1,-1],"loss_changes":[1.7528635E0,0E0,0E0],"parents":[2147483647,0,0],"right_children":[2,-1,-1],"split_conditions":[2.2239482E0,-6.1849006E-2,5.815767E-2],"split_indices":[16,0,0],"split_type":[0,0,0],"sum_hessian":[2.903526E0,1.6186867E0,1.2848393E0],"tree_param":{"num_deleted":"0","num_feature":"17","num_nodes":"3","size_leaf_vector":"1"}},{"base_weights":[-6.67691E-2,-5.967466E-2,5.609102E-2],"categories":[],"categories_nodes":[],"categories_segments":[],"categories_sizes":[],"default_left":[0,0,0],"id":73,"left_children":[1,-1,-1],"loss_changes":[1.557777E0,0E0,0E0],"parents":[2147483647,0,0],"right_children":[2,-1,-1],"split_conditions":[2.2239482E0,-5.967466E-2,5.609102E-2],"split_indices":[16,0,0],"split_type":[0,0,0],"sum_hessian":[2.6766388E0,1.4779886E0,1.1986504E0],"tree_param":{"num_deleted":"0","num_feature":"17","num_nodes":"3","size_leaf_vector":"1"}},{"base_weights":[-6.7524016E-2],"categories":[],"categories_nodes":[],"categories_segments":[],"categories_sizes":[],"default_left":[0],"id":74,"left_children":[-1],"loss_changes":[0E0],"parents":[2147483647],"right_children":[-1],"split_conditions":[-6.7524016E-3],"split_indices":[0],"split_type":[0],"sum_hessian":[2.5848827E0],"tree_param":{"num_deleted":"0","num_feature":"17","num_nodes":"1","size_leaf_vector":"1"}},{"base_weights":[-2.0728195E-2,-5.8538634E-2,5.827253E-2],"categories":[],"categories_nodes":[],"categories_segments":[],"categories_sizes":[],"default_left":[0,0,0],"id":75,"left_children":[1,-1,-1],"loss_changes":[1.601822E0,0E0,0E0],"parents":[2147483647,0,0],"right_children":[2,-1,-1],"split_conditions":[2.2239482E0,-5.8538634E-2,5.827253E-2],"split_indices":[16,0,0],"split_type":[0,0,0],"sum_hessian":[2.6998434E0,1.4102222E0,1.2896211E0],"tree_param":{"num_deleted":"0","num_feature":"17","num_nodes":"3","size_leaf_vector":"1"}},{"base_weights":[-4.0299795E-3,-5.7156026E-2,5.8051527E-2],"categories":[],"categories_nodes":[],"categories_segments":[],"categories_sizes":[],"default_left":[0,0,0],"id":76,"left_children":[1,-1,-1],"loss_changes":[1.5274256E0,0E0,0E0],"parents":[2147483647,0,0],"right_children":[2,-1,-1],"split_conditions":[2.2239482E0,-5.7156026E-2,5.8051527E-2],"split_indices":[16,0,0],"split_type":[0,0,0],"sum_hessian":[2.6040285E0,1.3325146E0,1.2715138E0],"tree_param":{"num_deleted":"0","num_feature":"17","num_nodes":"3","size_leaf_vector":"1"}},{"base_weights":[-7.3464913E-3],"categories":[],"categories_nodes":[],"categories_segments":[],"categories_sizes":[],"default_left":[0],"id":77,"left_children":[-1],"loss_changes":[0E0],"parents":[2147483647],"right_children":[-1],"split_conditions":[-7.3464913E-4],"split_indices":[0],"split_type":[0],"sum_hessian":[2.4358246E0],"tree_param":{"num_deleted":"0","num_feature":"17","num_nodes":"1","size_leaf_vector":"1"}},{"base_weights":[-3.2148E-2,-5.553664E-2,5.40878E-2],"categories":[],"categories_nodes":[],"categories_segments":[],"categories_sizes":[],"default_left":[0,0,0],"id":78,"left_children":[1,-1,-1],"loss_changes":[1.3066505E0,0E0,0E0],"parents":[2147483647,0,0],"right_children":[2,-1,-1],"split_conditions":[2.2239482E0,-5.553664E-2,5.40878E-2],"split_indices":[16,0,0],"split_type":[0,0,0],"sum_hessian":[2.3562562E0,1.2477653E0,1.108491E0],"tree_param":{"num_deleted":"0","num_feature":"17","num_nodes":"3","size_leaf_vector":"1"}},{"base_weights":[-4.025957E-2],"categories":[],"categories_nodes":[],"categories_segments":[],"categories_sizes":[],"default_left":[0],"id":79,"left_children":[-1],"loss_changes":[0E0],"parents":[2147483647],"right_children":[-1],"split_conditions":[-4.025957E-3],"split_indices":[0],"split_type":[0],"sum_hessian":[2.2338884E0],"tree_param":{"num_deleted":"0","num_feature":"17","num_nodes":"1","size_leaf_vector":"1"}},{"base_weights":[-4.3665748E-2,-5.3960353E-2,5.1477786E-2],"categories":[],"categories_nodes":[],"categories_segments":[],"categories_sizes":[],"default_left":[0,0,0],"id":80,"left_children":[1,-1,-1],"loss_changes":[1.1577013E0,0E0,0E0],"parents":[2147483647,0,0],"right_children":[2,-1,-1],"split_conditions":[2.2239482E0,-5.3960353E-2,5.1477786E-2],"split_indices":[16,0,0],"split_type":[0,0,0],"sum_hessian":[2.177162E0,1.1709826E0,1.0061795E0],"tree_param":{"num_deleted":"0","num_feature":"17","num_nodes":"3","size_leaf_vector":"1"}},{"base_weights":[-1.8537892E-2,-5.2714225E-2,5.213786E-2],"categories":[],"categories_nodes":[],"categories_segments":[],"categories_sizes":[],"default_left":[0,0,0],"id":81,"left_children":[1,-1,-1],"loss_changes":[1.1369615E0,0E0,0E0],"parents":[2147483647,0,0],"right_children":[2,-1,-1],"split_conditions":[2.2239482E0,-5.2714225E-2,5.213786E-2],"split_indices":[16,0,0],"split_type":[0,0,0],"sum_hessian":[2.1395073E0,1.1138829E0,1.0256243E0],"tree_param":{"num_deleted":"0","num_feature":"17","num_nodes":"3","size_leaf_vector":"1"}},{"base_weights":[1.0123734E-2,-5.156969E-2,5.309806E-2],"categories":[],"categories_nodes":[],"categories_segments":[],"categories_sizes":[],"default_left":[0,0,0],"id":82,"left_children":[1,-1,-1],"loss_changes":[1.1305665E0,0E0,0E0],"parents":[2147483647,0,0],"right_children":[2,-1,-1],"split_conditions":[2.2239482E0,-5.156969E-2,5.309806E-2],"split_indices":[16,0,0],"split_type":[0,0,0],"sum_hessian":[2.1281943E0,1.0639806E0,1.0642136E0],"tree_param":{"num_deleted":"0","num_feature":"17","num_nodes":"3","size_leaf_vector":"1"}},{"base_weights":[-2.0835845E-2],"categories":[],"categories_nodes":[],"categories_segments":[],"categories_sizes":[],"default_left":[0],"id":83,"left_children":[-1],"loss_changes":[0E0],"parents":[2147483647],"right_children":[-1],"split_conditions":[-2.0835844E-3],"split_indices":[0],"split_type":[0],"sum_hessian":[1.9483652E0],"tree_param":{"num_deleted":"0","num_feature":"17","num_nodes":"1","size_leaf_vector":"1"}},{"base_weights":[-8.2320515E-3],"categories":[],"categories_nodes":[],"categories_segments":[],"categories_sizes":[],"default_left":[0],"id":84,"left_children":[-1],"loss_changes":[0E0],"parents":[2147483647],"right_children":[-1],"split_conditions":[-8.2320516E-4],"split_indices":[0],"split_type":[0],"sum_hessian":[1.9670614E0],"tree_param":{"num_deleted":"0","num_feature":"17","num_nodes":"1","size_leaf_vector":"1"}},{"base_weights":[-5.481606E-2],"categories":[],"categories_nodes":[],"categories_segments":[],"categories_sizes":[],"default_left":[0],"id":85,"left_children":[-1],"loss_changes":[0E0],"parents":[2147483647],"right_children":[-1],"split_conditions":[-5.481606E-3],"split_indices":[0],"split_type":[0],"sum_hessian":[1.8423572E0],"tree_param":{"num_deleted":"0","num_feature":"17","num_nodes":"1","size_leaf_vector":"1"}},{"base_weights":[-1.4827277E-2],"categories":[],"categories_nodes":[],"categories_segments":[],"categories_sizes":[],"default_left":[0],"id":86,"left_children":[-1],"loss_changes":[0E0],"parents":[2147483647],"right_children":[-1],"split_conditions":[-1.4827277E-3],"split_indices":[0],"split_type":[0],"sum_hessian":[1.9260619E0],"tree_param":{"num_deleted":"0","num_feature":"17","num_nodes":"1","size_leaf_vector":"1"}},{"base_weights":[-7.6646437E-3],"categories":[],"categories_nodes":[],"categories_segments":[],"categories_sizes":[],"default_left":[0],"id":87,"left_children":[-1],"loss_changes":[0E0],"parents":[2147483647],"right_children":[-1],"split_conditions":[-7.664644E-4],"split_indices":[0],"split_type":[0],"sum_hessian":[1.9460666E0],"tree_param":{"num_deleted":"0","num_feature":"17","num_nodes":"1","size_leaf_vector":"1"}},{"base_weights":[-5.855039E-2],"categories":[],"categories_nodes":[],"categories_segments":[],"categories_sizes":[],"default_left":[0],"id":88,"left_children":[-1],"loss_changes":[0E0],"parents":[2147483647],"right_children":[-1],"split_conditions":[-5.855039E-3],"split_indices":[0],"split_type":[0],"sum_hessian":[1.8336523E0],"tree_param":{"num_deleted":"0","num_feature":"17","num_nodes":"1","size_leaf_vector":"1"}},{"base_weights":[-3.5364483E-2],"categories":[],"categories_nodes":[],"categories_segments":[],"categories_sizes":[],"default_left":[0],"id":89,"left_children":[-1],"loss_changes":[0E0],"parents":[2147483647],"right_children":[-1],"split_conditions":[-3.5364483E-3],"split_indices":[0],"split_type":[0],"sum_hessian":[1.8735822E0],"tree_param":{"num_deleted":"0","num_feature":"17","num_nodes":"1","size_leaf_vector":"1"}},{"base_weights":[2.3348182E-3],"categories":[],"categories_nodes":[],"categories_segments":[],"categories_sizes":[],"default_left":[0],"id":90,"left_children":[-1],"loss_changes":[0E0],"parents":[2147483647],"right_children":[-1],"split_conditions":[2.3348183E-4],"split_indices":[0],"split_type":[0],"sum_hessian":[1.9837228E0],"tree_param":{"num_deleted":"0","num_feature":"17","num_nodes":"1","size_leaf_vector":"1"}},{"base_weights":[-2.0511312E-2],"categories":[],"categories_nodes":[],"categories_segments":[],"categories_sizes":[],"default_left":[0],"id":91,"left_children":[-1],"loss_changes":[0E0],"parents":[2147483647],"right_children":[-1],"split_conditions":[-2.0511313E-3],"split_indices":[0],"split_type":[0],"sum_hessian":[1.9095562E0],"tree_param":{"num_deleted":"0","num_feature":"17","num_nodes":"1","size_leaf_vector":"1"}},{"base_weights":[-1.5043115E-2],"categories":[],"categories_nodes":[],"categories_segments":[],"categories_sizes":[],"default_left":[0],"id":92,"left_children":[-1],"loss_changes":[0E0],"parents":[2147483647],"right_children":[-1],"split_conditions":[-1.5043116E-3],"split_indices":[0],"split_type":[0],"sum_hessian":[1.8783393E0],"tree_param":{"num_deleted":"0","num_feature":"17","num_nodes":"1","size_leaf_vector":"1"}},{"base_weights":[-7.306433E-2],"categories":[],"categories_nodes":[],"categories_segments":[],"categories_sizes":[],"default_left":[0],"id":93,"left_children":[-1],"loss_changes":[0E0],"parents":[2147483647],"right_children":[-1],"split_conditions":[-7.306433E-3],"split_indices":[0],"split_type":[0],"sum_hessian":[1.7373286E0],"tree_param":{"num_deleted":"0","num_feature":"17","num_nodes":"1","size_leaf_vector":"1"}},{"base_weights":[7.051096E-3],"categories":[],"categories_nodes":[],"categories_segments":[],"categories_sizes":[],"default_left":[0],"id":94,"left_children":[-1],"loss_changes":[0E0],"parents":[2147483647],"right_children":[-1],"split_conditions":[7.051096E-4],"split_indices":[0],"split_type":[0],"sum_hessian":[1.9455963E0],"tree_param":{"num_deleted":"0","num_feature":"17","num_nodes":"1","size_leaf_vector":"1"}},{"base_weights":[-3.5024323E-2],"categories":[],"categories_nodes":[],"categories_segments":[],"categories_sizes":[],"default_left":[0],"id":95,"left_children":[-1],"loss_changes":[0E0],"parents":[2147483647],"right_children":[-1],"split_conditions":[-3.5024323E-3],"split_indices":[0],"split_type":[0],"sum_hessian":[1.8334782E0],"tree_param":{"num_deleted":"0","num_feature":"17","num_nodes":"1","size_leaf_vector":"1"}},{"base_weights":[-1.1837637E-2],"categories":[],"categories_nodes":[],"categories_segments":[],"categories_sizes":[],"default_left":[0],"id":96,"left_children":[-1],"loss_changes":[0E0],"parents":[2147483647],"right_children":[-1],"split_conditions":[-1.1837637E-3],"split_indices":[0],"split_type":[0],"sum_hessian":[1.90533E0],"tree_param":{"num_deleted":"0","num_feature":"17","num_nodes":"1","size_leaf_vector":"1"}},{"base_weights":[1.2190151E-2],"categories":[],"categories_nodes":[],"categories_segments":[],"categories_sizes":[],"default_left":[0],"id":97,"left_children":[-1],"loss_changes":[0E0],"parents":[2147483647],"right_children":[-1],"split_conditions":[1.2190151E-3],"split_indices":[0],"split_type":[0],"sum_hessian":[1.9708006E0],"tree_param":{"num_deleted":"0","num_feature":"17","num_nodes":"1","size_leaf_vector":"1"}},{"base_weights":[-2.1755775E-2],"categories":[],"categories_nodes":[],"categories_segments":[],"categories_sizes":[],"default_left":[0],"id":98,"left_children":[-1],"loss_changes":[0E0],"parents":[2147483647],"right_children":[-1],"split_conditions":[-2.1755777E-3],"split_indices":[0],"split_type":[0],"sum_hessian":[1.8436648E0],"tree_param":{"num_deleted":"0","num_feature":"17","num_nodes":"1","size_leaf_vector":"1"}},{"base_weights":[-5.677412E-2],"categories":[],"categories_nodes":[],"categories_segments":[],"categories_sizes":[],"default_left":[0],"id":99,"left_children":[-1],"loss_changes":[0E0],"parents":[2147483647],"right_children":[-1],"split_conditions":[-5.6774123E-3],"split_indices":[0],"split_type":[0],"sum_hessian":[1.7581983E0],"tree_param":{"num_deleted":"0","num_feature":"17","num_nodes":"1","size_leaf_vector":"1"}}]},"name":"gbtree"},"learner_model_param":{"base_score":"2.1049078E-1","boost_from_average":"1","num_class":"0","num_feature":"17","num_target":"1"},"objective":{"name":"binary:logistic","reg_loss_param":{"scale_pos_weight":"1"}}},"version":[2,1,4]}